[
  {
    "id": "TCH-7284",
    "name": "Prof. Sarah Johnson",
    "email": "sarah.johnson@grademaster.edu",
    "username": "sarah_johnson",
    "password": "Sarah@7284",
    "designation": "Professor",
    "department": "Academic Department",
    "joinDate": "2023-08-01",
    "experience": "2+ years",
    "contact": {
      "phone": "+91 98765 43210",
      "address": "GradeMaster Institution, Chennai"
    },
    "subjects": ["Mathematics", "Science"],
    "badges": ["efficient-evaluator", "dedicated-educator"]
  },
  {
    "id": "TCH-7285",
    "name": "Mr. David Lee",
    "email": "david.lee@grademaster.edu",
    "username": "david_lee",
    "password": "David#7285",
    "designation": "Senior Teacher",
    "department": "Academic Department",
    "joinDate": "2023-09-15",
    "experience": "3+ years",
    "contact": {
      "phone": "+91 98765 43211",
      "address": "GradeMaster Institution, Chennai"
    },
    "subjects": ["English", "Social Science"],
    "badges": ["active-evaluator", "consistent-performer"]
  }
]